.env_sample
.gitignore
.pylintrc
LICENCE
README.md
logging.conf
mypy.ini
pyproject.toml
requirements.txt
setup.cfg
setup.py
.github/workflows/pull-request.yaml
.github/workflows/python-publish.yml
example/__init__.py
example/fetch.py
example/load_dashboard.py
example/query.sql
example/update_dashboard.py
example/dashboard/_config.json
example/dashboard/base_query.sql
example/dashboard/blocks-between.sql
example/dashboard/enum-demo-max-price.sql
example/dashboard/query1.sql
example/dashboard/query2-polygon.sql
tests/e2e/test_dashboard_load.py
tests/e2e/test_dashboard_update.py
tests/e2e/test_dune_api.py
tests/queries/test_query.sql
tests/unit/test_dashboard.py
tests/unit/test_dune.py
tests/unit/test_response.py
tests/unit/test_types.py
tests/unit/test_util.py
updated_networks_dune/__init__.py
updated_networks_dune/api.py
updated_networks_dune/constants.py
updated_networks_dune/dashboard.py
updated_networks_dune/file_io.py
updated_networks_dune/logger.py
updated_networks_dune/py.typed
updated_networks_dune/response.py
updated_networks_dune/types.py
updated_networks_dune/util.py
updated_networks_dune.egg-info/PKG-INFO
updated_networks_dune.egg-info/SOURCES.txt
updated_networks_dune.egg-info/dependency_links.txt
updated_networks_dune.egg-info/not-zip-safe
updated_networks_dune.egg-info/requires.txt
updated_networks_dune.egg-info/top_level.txt