Metadata-Version: 2.1
Name: updated-networks-dune
Version: 0.1.dev1
Summary: A simple framework for interacting with Dune Analytics unsupported API.
Home-page: https://github.com/atananetwork/dune-api-fork
Author: Kevin
Author-email: kevin@operator.io
License: Apache License Version 2.0
Classifier: Programming Language :: Python :: 3
Classifier: License :: OSI Approved :: Apache Software License
Classifier: Operating System :: OS Independent
Requires-Python: >=3.9
License-File: LICENCE
